daepy/__init__.py
daepy/bvp.py
daepy/collocation.py
daepy/continuation.py
daepy/dae.py
daepy/derivatives.py
daepy/nonlinear.py
daepy/cheby/__init__.py
daepy/cheby/cheby.cpython-37m-darwin.so
daepy/cheby/setup.py
daepy-1.0.1.dist-info/LICENSE
daepy-1.0.1.dist-info/METADATA
daepy-1.0.1.dist-info/WHEEL
daepy-1.0.1.dist-info/top_level.txt
daepy-1.0.1.dist-info/RECORD
