Metadata-Version: 2.1
Name: daepy
Version: 1.0.1
Summary: A Python library for solving boundary value problems of differential algebraic equations with advanced and retarded (forward and backward) delays
Home-page: https://lcvmwww.epfl.ch/software/daepy
Author: Alastair Flynn
Author-email: contact@alastairflynn.com
License: UNKNOWN
Project-URL: Documentation, https://lcvmwww.epfl.ch/software/daepy
Project-URL: Source code, https://github.com/alastairflynn/daepy
Platform: UNKNOWN
Classifier: Programming Language :: Python :: 3
Classifier: License :: OSI Approved :: MIT License
Requires-Python: >=3.5
Requires-Dist: numpy (>=1.4.0)
Requires-Dist: scipy (>=1.0.0)
Requires-Dist: matplotlib (>=3.0)
Requires-Dist: dill
